notion_kit/CONTENTS.py
notion_kit/__init__.py
notion_kit/api.py
notion_kit/dict_gadget.py
notion_kit/gadget.py
notion_kit/object.py
notion_kit/tool.py
notion_kit-1.1.0.dist-info/LICENSE
notion_kit-1.1.0.dist-info/METADATA
notion_kit-1.1.0.dist-info/WHEEL
notion_kit-1.1.0.dist-info/top_level.txt
notion_kit-1.1.0.dist-info/RECORD
