Metadata-Version: 2.1
Name: notion-kit
Version: 1.1.0
Summary: For easy use notion-sdk-py
Home-page: https://github.com/bluewhitep/Notion_kit
Author: Jieqiang Zhang
Author-email: bluewhite2389@gmail.com
License: MIT
Classifier: Programming Language :: Python :: 3.10
Classifier: Development Status :: 3 - Alpha
Classifier: License :: OSI Approved :: MIT License
Requires-Python: >=3.10, <4
License-File: LICENSE
Requires-Dist: pytz
Requires-Dist: notion-client (>=2.0.0)
